odoo8_addon_stock_inventory_exclude_sublocation-8.0.1.0.0-py2.7-nspkg.pth
odoo8_addon_stock_inventory_exclude_sublocation-8.0.1.0.0.dist-info/DESCRIPTION.rst
odoo8_addon_stock_inventory_exclude_sublocation-8.0.1.0.0.dist-info/METADATA
odoo8_addon_stock_inventory_exclude_sublocation-8.0.1.0.0.dist-info/RECORD
odoo8_addon_stock_inventory_exclude_sublocation-8.0.1.0.0.dist-info/WHEEL
odoo8_addon_stock_inventory_exclude_sublocation-8.0.1.0.0.dist-info/metadata.json
odoo8_addon_stock_inventory_exclude_sublocation-8.0.1.0.0.dist-info/namespace_packages.txt
odoo8_addon_stock_inventory_exclude_sublocation-8.0.1.0.0.dist-info/top_level.txt
odoo_addons/stock_inventory_exclude_sublocation/README.rst
odoo_addons/stock_inventory_exclude_sublocation/__init__.py
odoo_addons/stock_inventory_exclude_sublocation/__openerp__.py
odoo_addons/stock_inventory_exclude_sublocation/i18n/de.po
odoo_addons/stock_inventory_exclude_sublocation/i18n/es.po
odoo_addons/stock_inventory_exclude_sublocation/i18n/es_ES.po
odoo_addons/stock_inventory_exclude_sublocation/i18n/fr.po
odoo_addons/stock_inventory_exclude_sublocation/i18n/it.po
odoo_addons/stock_inventory_exclude_sublocation/i18n/pt_BR.po
odoo_addons/stock_inventory_exclude_sublocation/i18n/sk.po
odoo_addons/stock_inventory_exclude_sublocation/i18n/sl.po
odoo_addons/stock_inventory_exclude_sublocation/models/__init__.py
odoo_addons/stock_inventory_exclude_sublocation/models/stock_inventory.py
odoo_addons/stock_inventory_exclude_sublocation/static/description/icon.png
odoo_addons/stock_inventory_exclude_sublocation/tests/__init__.py
odoo_addons/stock_inventory_exclude_sublocation/tests/test_exclude_sublocation.py
odoo_addons/stock_inventory_exclude_sublocation/views/stock_inventory_view.xml
